sk8o_sim/__init__.py
sk8o_sim/common.py
sk8o_sim/configs.py
sk8o_sim/controllers.py
sk8o_sim/full/__init__.py
sk8o_sim/full/data.py
sk8o_sim/full/robot.py
sk8o_sim/full/simulation.py
sk8o_sim/full/view.py
sk8o_sim/full/model/body.obj
sk8o_sim/full/model/body.stl
sk8o_sim/full/model/body_black.stl
sk8o_sim/full/model/body_blue.stl
sk8o_sim/full/model/leg_link.stl
sk8o_sim/full/model/lower_leg_R.stl
sk8o_sim/full/model/rim.stl
sk8o_sim/full/model/scene.xml
sk8o_sim/full/model/sk8o_model.xml
sk8o_sim/full/model/tire.stl
sk8o_sim/full/model/upper_leg_R.stl
sk8o_sim/full/model/wheel.stl
sk8o_sim/segway/OpenSans-Regular.ttf
sk8o_sim/segway/__init__.py
sk8o_sim/segway/data.py
sk8o_sim/segway/simulation.py
sk8o_sim/segway/view.py
sk8o_sim-0.1.8.dist-info/METADATA
sk8o_sim-0.1.8.dist-info/WHEEL
sk8o_sim-0.1.8.dist-info/licenses/LICENSE
sk8o_sim-0.1.8.dist-info/RECORD
