Metadata-Version: 2.1
Name: sk8o_sim
Version: 0.1.8
Summary: A set of two simulation environments for robot SK8O developed at FEE CTU in Prague.
Author-email: Dominik Hodan <hodandom@fel.cvut.cz>
License-File: LICENSE
Classifier: License :: OSI Approved :: MIT License
Classifier: Operating System :: OS Independent
Classifier: Programming Language :: Python :: 3
Requires-Python: >=3.11
Requires-Dist: control>=0.9
Requires-Dist: mujoco-python-viewer>=0.1.0
Requires-Dist: mujoco>=2.3.5
Requires-Dist: numpy>=1.25
Requires-Dist: omegaconf>=2.3.0
Requires-Dist: pygame
Requires-Dist: sympy
